{
  "data": [
    {
      "id": "8235219",
      "source_ids": {
        "footystats": "8235219",
        "sportmonks": ""
      },
      "home_name": "UD Las Palmas",
      "away_name": "Granada CF",
      "competition_name": "",
      "competition_id": 15066,
      "league_country": "",
      "league_country_image": "",
      "date_unix": 1775149200,
      "home_image": "teams/spain-ud-las-palmas.png",
      "away_image": "teams/spain-granada-cf.png",
      "home_country": "Spain",
      "away_country": "Spain",
      "venue_name": "Estadio de Gran Canaria",
      "venue_city": "Avenida Pío XII 29, Las Palmas de Gran Canaria",
      "referee_name": "",
      "weather": {},
      "home_ppg": 1.81,
      "away_ppg": 1.27,
      "team_a_xg_prematch": 1.47,
      "team_b_xg_prematch": 1.17,
      "btts_potential": 49.0,
      "o25_potential": 46.0,
      "o05HT_potential": 81.0,
      "odds_ft_1": 1.9,
      "odds_ft_x": 3.2,
      "odds_ft_2": 4.2,
      "homeGoalCount": 0,
      "awayGoalCount": 0,
      "status": "incomplete",
      "elapsed": 0,
      "boss_ai_decision": "STATUS: RISKY. Critical data (odds for O2.5/BTTS/FH O0.5, model predictions, standings, H2H, key sidelined players) is missing.\nREASON: Insufficient corroborating data prevents robust cross-checking and accurate risk assessment. Odds for several core markets are absent.\nCONCLUSION: No Bet / Skip.",
      "prematch_comment": "STATUS: RISKY. Critical data (odds for O2.5/BTTS/FH O0.5, model predictions, standings, H2H, key sidelined players) is missing.\nREASON: Insufficient corroborating data prevents robust cross-checking and accurate risk assessment. Odds for several core markets are absent.\nCONCLUSION: No Bet / Skip.",
      "ai_comment": "STATUS: RISKY. Critical data (odds for O2.5/BTTS/FH O0.5, model predictions, standings, H2H, key sidelined players) is missing.\nREASON: Insufficient corroborating data prevents robust cross-checking and accurate risk assessment. Odds for several core markets are absent.\nCONCLUSION: No Bet / Skip."
    },
    {
      "id": "8235083",
      "source_ids": {
        "footystats": "8235083",
        "sportmonks": ""
      },
      "home_name": "CD Castellón",
      "away_name": "Almería",
      "competition_name": "",
      "competition_id": 15066,
      "league_country": "",
      "league_country_image": "",
      "date_unix": 1775152800,
      "home_image": "teams/spain-cd-castellon.png",
      "away_image": "teams/spain-ud-almeria.png",
      "home_country": "Spain",
      "away_country": "Spain",
      "venue_name": "Nou Estadi Castalia",
      "venue_city": "Calle de Huesca, Castellón de la Plana",
      "referee_name": "",
      "weather": {},
      "home_ppg": 2.0,
      "away_ppg": 1.44,
      "team_a_xg_prematch": 1.76,
      "team_b_xg_prematch": 1.49,
      "btts_potential": 65.0,
      "o25_potential": 52.0,
      "o05HT_potential": 71.0,
      "odds_ft_1": 1.96,
      "odds_ft_x": 3.86,
      "odds_ft_2": 3.2,
      "homeGoalCount": 0,
      "awayGoalCount": 0,
      "status": "incomplete",
      "elapsed": 0,
      "boss_ai_decision": "STATUS: RISKY\nREASON: Critical data points are missing, including full bookmaker odds for goal markets, model predictions, league standings, H2H, and key player information. Insufficient data for robust analysis and risk assessment.\nCONCLUSION: No Bet / Skip",
      "prematch_comment": "STATUS: RISKY\nREASON: Critical data points are missing, including full bookmaker odds for goal markets, model predictions, league standings, H2H, and key player information. Insufficient data for robust analysis and risk assessment.\nCONCLUSION: No Bet / Skip",
      "ai_comment": "STATUS: RISKY\nREASON: Critical data points are missing, including full bookmaker odds for goal markets, model predictions, league standings, H2H, and key player information. Insufficient data for robust analysis and risk assessment.\nCONCLUSION: No Bet / Skip"
    },
    {
      "id": "8235095",
      "source_ids": {
        "footystats": "8235095",
        "sportmonks": ""
      },
      "home_name": "Real Sociedad II",
      "away_name": "SD Eibar",
      "competition_name": "",
      "competition_id": 15066,
      "league_country": "",
      "league_country_image": "",
      "date_unix": 1775152800,
      "home_image": "teams/spain-real-sociedad-de-futbol-ii.png",
      "away_image": "teams/spain-sd-eibar.png",
      "home_country": "Spain",
      "away_country": "Spain",
      "venue_name": "Estadio Municipal de Anoeta",
      "venue_city": "Paseo de Anoeta 1, Donostia-San Sebastián",
      "referee_name": "",
      "weather": {},
      "home_ppg": 1.63,
      "away_ppg": 0.73,
      "team_a_xg_prematch": 1.29,
      "team_b_xg_prematch": 1.0,
      "btts_potential": 48.0,
      "o25_potential": 39.0,
      "o05HT_potential": 74.0,
      "odds_ft_1": 3.0,
      "odds_ft_x": 3.0,
      "odds_ft_2": 2.56,
      "homeGoalCount": 0,
      "awayGoalCount": 0,
      "status": "incomplete",
      "elapsed": 0,
      "boss_ai_decision": "STATUS: RISKY\nREASON: Critical data missing: Model predictions, league standings, H2H, and key sidelined players. Bookmaker odds for match result contradict PPG data. Missing odds for Over 2.5 and BTTS markets.\nCONCLUSION: No Bet / Skip",
      "prematch_comment": "STATUS: RISKY\nREASON: Critical data missing: Model predictions, league standings, H2H, and key sidelined players. Bookmaker odds for match result contradict PPG data. Missing odds for Over 2.5 and BTTS markets.\nCONCLUSION: No Bet / Skip",
      "ai_comment": "STATUS: RISKY\nREASON: Critical data missing: Model predictions, league standings, H2H, and key sidelined players. Bookmaker odds for match result contradict PPG data. Missing odds for Over 2.5 and BTTS markets.\nCONCLUSION: No Bet / Skip"
    },
    {
      "id": "8419024",
      "source_ids": {
        "footystats": "8419024",
        "sportmonks": ""
      },
      "home_name": "Barracas Central",
      "away_name": "Sarmiento",
      "competition_name": "",
      "competition_id": 16571,
      "league_country": "",
      "league_country_image": "",
      "date_unix": 1775152800,
      "home_image": "teams/argentina-ca-barracas-central.png",
      "away_image": "teams/argentina-ca-sarmiento.png",
      "home_country": "Argentina",
      "away_country": "Argentina",
      "venue_name": "Estadio Claudio Chiqui Tapia",
      "venue_city": "Avenida Olavaría 3400 y Luna, Bairro Barracas, Capital Federal, Ciudad de Buenos Aires",
      "referee_name": "",
      "weather": {},
      "home_ppg": 1.45,
      "away_ppg": 1.18,
      "team_a_xg_prematch": 1.18,
      "team_b_xg_prematch": 1.29,
      "btts_potential": 36.0,
      "o25_potential": 27.0,
      "o05HT_potential": 60.0,
      "odds_ft_1": 2.3,
      "odds_ft_x": 2.8,
      "odds_ft_2": 3.45,
      "homeGoalCount": 0,
      "awayGoalCount": 0,
      "status": "incomplete",
      "elapsed": 0,
      "boss_ai_decision": "STATUS: RISKY\nREASON: Significant missing data (Model Predictions, Standings, H2H, O2.5/BTTS odds). xG (Away slightly higher) contradicts PPG (Home significantly better) and market odds (Home favorite).\nCONCLUSION: No Bet / Skip",
      "prematch_comment": "STATUS: RISKY\nREASON: Significant missing data (Model Predictions, Standings, H2H, O2.5/BTTS odds). xG (Away slightly higher) contradicts PPG (Home significantly better) and market odds (Home favorite).\nCONCLUSION: No Bet / Skip",
      "ai_comment": "STATUS: RISKY\nREASON: Significant missing data (Model Predictions, Standings, H2H, O2.5/BTTS odds). xG (Away slightly higher) contradicts PPG (Home significantly better) and market odds (Home favorite).\nCONCLUSION: No Bet / Skip"
    },
    {
      "id": "8432111",
      "source_ids": {
        "footystats": "8432111",
        "sportmonks": ""
      },
      "home_name": "Boyacá Chicó",
      "away_name": "Deportivo Pereira",
      "competition_name": "",
      "competition_id": 16614,
      "league_country": "",
      "league_country_image": "",
      "date_unix": 1775156400,
      "home_image": "teams/colombia-deportivo-boyaca-chico-fc-sa.png",
      "away_image": "teams/colombia-cs-deportiva-y-cultural-de-pereira.png",
      "home_country": "Colombia",
      "away_country": "Colombia",
      "venue_name": "",
      "venue_city": "",
      "referee_name": "",
      "weather": {},
      "home_ppg": 0.62,
      "away_ppg": 0.46,
      "team_a_xg_prematch": 0.93,
      "team_b_xg_prematch": 0.93,
      "btts_potential": 43.0,
      "o25_potential": 50.0,
      "o05HT_potential": 77.0,
      "odds_ft_1": 1.92,
      "odds_ft_x": 3.35,
      "odds_ft_2": 3.25,
      "homeGoalCount": 0,
      "awayGoalCount": 0,
      "status": "incomplete",
      "elapsed": 0,
      "boss_ai_decision": "STATUS: RISKY\nREASON: Significant conflict between xG (even match) and bookmaker odds (strong home favorite). Crucial data missing including model predictions, standings, H2H, and key player information.\nCONCLUSION: No Bet / Skip",
      "prematch_comment": "STATUS: RISKY\nREASON: Significant conflict between xG (even match) and bookmaker odds (strong home favorite). Crucial data missing including model predictions, standings, H2H, and key player information.\nCONCLUSION: No Bet / Skip",
      "ai_comment": "STATUS: RISKY\nREASON: Significant conflict between xG (even match) and bookmaker odds (strong home favorite). Crucial data missing including model predictions, standings, H2H, and key player information.\nCONCLUSION: No Bet / Skip"
    },
    {
      "id": "8235094",
      "source_ids": {
        "footystats": "8235094",
        "sportmonks": ""
      },
      "home_name": "Leganés",
      "away_name": "Real Zaragoza",
      "competition_name": "",
      "competition_id": 15066,
      "league_country": "",
      "league_country_image": "",
      "date_unix": 1775158200,
      "home_image": "teams/spain-cd-leganes.png",
      "away_image": "teams/spain-real-zaragoza.png",
      "home_country": "Spain",
      "away_country": "Spain",
      "venue_name": "Estadio Municipal de Butarque",
      "venue_city": "Calle Arquitectura, Leganés",
      "referee_name": "",
      "weather": {},
      "home_ppg": 1.27,
      "away_ppg": 1.0,
      "team_a_xg_prematch": 1.48,
      "team_b_xg_prematch": 1.28,
      "btts_potential": 45.0,
      "o25_potential": 36.0,
      "o05HT_potential": 74.0,
      "odds_ft_1": 1.92,
      "odds_ft_x": 3.05,
      "odds_ft_2": 3.66,
      "homeGoalCount": 0,
      "awayGoalCount": 0,
      "status": "incomplete",
      "elapsed": 0,
      "boss_ai_decision": "STATUS: RISKY\nREASON: Significant data gaps exist for model predictions, league standings, H2H results, key sidelined players, and crucial odds (Over 2.5, BTTS). Incomplete information prevents comprehensive risk assessment.\nCONCLUSION: No Bet / Skip",
      "prematch_comment": "STATUS: RISKY\nREASON: Significant data gaps exist for model predictions, league standings, H2H results, key sidelined players, and crucial odds (Over 2.5, BTTS). Incomplete information prevents comprehensive risk assessment.\nCONCLUSION: No Bet / Skip",
      "ai_comment": "STATUS: RISKY\nREASON: Significant data gaps exist for model predictions, league standings, H2H results, key sidelined players, and crucial odds (Over 2.5, BTTS). Incomplete information prevents comprehensive risk assessment.\nCONCLUSION: No Bet / Skip"
    },
    {
      "id": "8419018",
      "source_ids": {
        "footystats": "8419018",
        "sportmonks": ""
      },
      "home_name": "Tigre",
      "away_name": "Independiente Rivadavia",
      "competition_name": "",
      "competition_id": 16571,
      "league_country": "",
      "league_country_image": "",
      "date_unix": 1775161800,
      "home_image": "teams/argentina-ca-tigre.png",
      "away_image": "teams/argentina-cs-independiente-rivadavia.png",
      "home_country": "Argentina",
      "away_country": "Argentina",
      "venue_name": "Estadio José Dellagiovanna",
      "venue_city": "Avenida Presidente Perón 2650 esq. Guido Spano 1053, Victoria, San Fernando, Provincia de Buenos Aires",
      "referee_name": "",
      "weather": {},
      "home_ppg": 1.55,
      "away_ppg": 2.09,
      "team_a_xg_prematch": 1.55,
      "team_b_xg_prematch": 1.6,
      "btts_potential": 69.0,
      "o25_potential": 46.0,
      "o05HT_potential": 73.0,
      "odds_ft_1": 2.3,
      "odds_ft_x": 2.9,
      "odds_ft_2": 3.4,
      "homeGoalCount": 0,
      "awayGoalCount": 0,
      "status": "incomplete",
      "elapsed": 0,
      "boss_ai_decision": "STATUS: RISKY.\nREASON: Critical data points are missing (model predictions, standings, H2H, injuries). `Over 2.5` and `BTTS` odds are unavailable. `BTTS` potential (69%) conflicts with `Over 2.5` potential (46%). Insufficient data for confident analysis.\nCONCLUSION: No Bet / Skip.",
      "prematch_comment": "STATUS: RISKY.\nREASON: Critical data points are missing (model predictions, standings, H2H, injuries). `Over 2.5` and `BTTS` odds are unavailable. `BTTS` potential (69%) conflicts with `Over 2.5` potential (46%). Insufficient data for confident analysis.\nCONCLUSION: No Bet / Skip.",
      "ai_comment": "STATUS: RISKY.\nREASON: Critical data points are missing (model predictions, standings, H2H, injuries). `Over 2.5` and `BTTS` odds are unavailable. `BTTS` potential (69%) conflicts with `Over 2.5` potential (46%). Insufficient data for confident analysis.\nCONCLUSION: No Bet / Skip."
    },
    {
      "id": "8469790",
      "source_ids": {
        "footystats": "8469790",
        "sportmonks": ""
      },
      "home_name": "São Bernardo",
      "away_name": "Operário PR",
      "competition_name": "",
      "competition_id": 16783,
      "league_country": "",
      "league_country_image": "",
      "date_unix": 1775161800,
      "home_image": "teams/brazil-sao-bernardo-fc.png",
      "away_image": "teams/brazil-operario-ferroviario-ec.png",
      "home_country": "Brazil",
      "away_country": "Brazil",
      "venue_name": "Estádio Primeiro de Maio",
      "venue_city": "Rua Olavo Bilac 240, São Bernardo do Campo, São Paulo",
      "referee_name": "",
      "weather": {},
      "home_ppg": 0.0,
      "away_ppg": 0.0,
      "team_a_xg_prematch": 0.0,
      "team_b_xg_prematch": 0.0,
      "btts_potential": 0.0,
      "o25_potential": 0.0,
      "o05HT_potential": 0.0,
      "odds_ft_1": 2.27,
      "odds_ft_x": 2.97,
      "odds_ft_2": 3.37,
      "homeGoalCount": 0,
      "awayGoalCount": 0,
      "status": "incomplete",
      "elapsed": 0,
      "boss_ai_decision": "",
      "prematch_comment": "",
      "ai_comment": ""
    },
    {
      "id": "8432413",
      "source_ids": {
        "footystats": "8432413",
        "sportmonks": ""
      },
      "home_name": "Universidad Católica",
      "away_name": "Palestino",
      "competition_name": "",
      "competition_id": 16615,
      "league_country": "",
      "league_country_image": "",
      "date_unix": 1775163600,
      "home_image": "teams/chile-cd-universidad-catolica.png",
      "away_image": "teams/chile-cd-palestino.png",
      "home_country": "Chile",
      "away_country": "Chile",
      "venue_name": "Estadio San Carlos de Apoquindo",
      "venue_city": "Camino Las Flores 13000, sector San Carlos de Apoquindo, Las Condes, Santiago de Chile",
      "referee_name": "",
      "weather": {},
      "home_ppg": 2.33,
      "away_ppg": 0.0,
      "team_a_xg_prematch": 1.32,
      "team_b_xg_prematch": 1.38,
      "btts_potential": 67.0,
      "o25_potential": 67.0,
      "o05HT_potential": 67.0,
      "odds_ft_1": 1.83,
      "odds_ft_x": 3.5,
      "odds_ft_2": 3.9,
      "homeGoalCount": 0,
      "awayGoalCount": 0,
      "status": "incomplete",
      "elapsed": 0,
      "boss_ai_decision": "STATUS: RISKY\nREASON: Away team's PPG is 0.0, indicating unreliable or incomplete data. Significant missing information includes league standings, H2H, key player news, and full market odds. Data integrity is compromised.\nCONCLUSION: No Bet / Skip",
      "prematch_comment": "STATUS: RISKY\nREASON: Away team's PPG is 0.0, indicating unreliable or incomplete data. Significant missing information includes league standings, H2H, key player news, and full market odds. Data integrity is compromised.\nCONCLUSION: No Bet / Skip",
      "ai_comment": "STATUS: RISKY\nREASON: Away team's PPG is 0.0, indicating unreliable or incomplete data. Significant missing information includes league standings, H2H, key player news, and full market odds. Data integrity is compromised.\nCONCLUSION: No Bet / Skip"
    },
    {
      "id": "8432113",
      "source_ids": {
        "footystats": "8432113",
        "sportmonks": ""
      },
      "home_name": "América de Cali",
      "away_name": "Atlético Bucaramanga",
      "competition_name": "",
      "competition_id": 16614,
      "league_country": "",
      "league_country_image": "",
      "date_unix": 1775164200,
      "home_image": "teams/colombia-sociedad-anonima-deportiva-america-sa.png",
      "away_image": "teams/colombia-ca-bucaramanga.png",
      "home_country": "Colombia",
      "away_country": "Colombia",
      "venue_name": "Estadio Olímpico Pascual Guerrero",
      "venue_city": "Carrera 36 entre Calles 5 y 5B3, Santiago de Cali",
      "referee_name": "",
      "weather": {},
      "home_ppg": 1.62,
      "away_ppg": 1.46,
      "team_a_xg_prematch": 1.58,
      "team_b_xg_prematch": 1.34,
      "btts_potential": 42.0,
      "o25_potential": 46.0,
      "o05HT_potential": 73.0,
      "odds_ft_1": 1.82,
      "odds_ft_x": 3.2,
      "odds_ft_2": 4.33,
      "homeGoalCount": 0,
      "awayGoalCount": 0,
      "status": "incomplete",
      "elapsed": 0,
      "boss_ai_decision": "STATUS: RISKY / DATA INCOMPLETE\nREASON: Critical data including model predictions, standings, H2H results, and key sidelined players are absent. Over 2.5 and BTTS odds are also missing. This prohibits a comprehensive, low-risk assessment.\nCONCLUSION: No Bet / Skip",
      "prematch_comment": "STATUS: RISKY / DATA INCOMPLETE\nREASON: Critical data including model predictions, standings, H2H results, and key sidelined players are absent. Over 2.5 and BTTS odds are also missing. This prohibits a comprehensive, low-risk assessment.\nCONCLUSION: No Bet / Skip",
      "ai_comment": "STATUS: RISKY / DATA INCOMPLETE\nREASON: Critical data including model predictions, standings, H2H results, and key sidelined players are absent. Over 2.5 and BTTS odds are also missing. This prohibits a comprehensive, low-risk assessment.\nCONCLUSION: No Bet / Skip"
    },
    {
      "id": "8409766",
      "source_ids": {
        "footystats": "8409766",
        "sportmonks": ""
      },
      "home_name": "Chapecoense",
      "away_name": "Atlético Mineiro",
      "competition_name": "",
      "competition_id": 16544,
      "league_country": "",
      "league_country_image": "",
      "date_unix": 1775167200,
      "home_image": "teams/brazil-chapecoense-af.png",
      "away_image": "teams/brazil-ca-mineiro.png",
      "home_country": "Brazil",
      "away_country": "Brazil",
      "venue_name": "Arena Condá",
      "venue_city": "Rua Clevelândia, Bairro Centro, Chapecó, Santa Catarina",
      "referee_name": "",
      "weather": {},
      "home_ppg": 1.5,
      "away_ppg": 0.0,
      "team_a_xg_prematch": 1.36,
      "team_b_xg_prematch": 1.24,
      "btts_potential": 50.0,
      "o25_potential": 38.0,
      "o05HT_potential": 75.0,
      "odds_ft_1": 2.87,
      "odds_ft_x": 3.3,
      "odds_ft_2": 2.42,
      "homeGoalCount": 0,
      "awayGoalCount": 0,
      "status": "incomplete",
      "elapsed": 0,
      "boss_ai_decision": "STATUS: RISKY.\nREASON: Significant data gaps. Atlético Mineiro's PPG (0.0) is highly suspect. Missing league standings, H2H, and specific odds for O2.5/BTTS prevent comprehensive analysis and create substantial uncertainty.\nCONCLUSION: No Bet / Skip.",
      "prematch_comment": "STATUS: RISKY.\nREASON: Significant data gaps. Atlético Mineiro's PPG (0.0) is highly suspect. Missing league standings, H2H, and specific odds for O2.5/BTTS prevent comprehensive analysis and create substantial uncertainty.\nCONCLUSION: No Bet / Skip.",
      "ai_comment": "STATUS: RISKY.\nREASON: Significant data gaps. Atlético Mineiro's PPG (0.0) is highly suspect. Missing league standings, H2H, and specific odds for O2.5/BTTS prevent comprehensive analysis and create substantial uncertainty.\nCONCLUSION: No Bet / Skip."
    },
    {
      "id": "8409774",
      "source_ids": {
        "footystats": "8409774",
        "sportmonks": ""
      },
      "home_name": "Santos",
      "away_name": "Remo",
      "competition_name": "",
      "competition_id": 16544,
      "league_country": "",
      "league_country_image": "",
      "date_unix": 1775167200,
      "home_image": "teams/brazil-santos-fc-sao-paulo.png",
      "away_image": "teams/brazil-clube-do-remo.png",
      "home_country": "Brazil",
      "away_country": "Brazil",
      "venue_name": "Estádio Urbano Caldeira",
      "venue_city": "Rue Princesa Isabel 77, Vila Belmiro, Santos, São Paulo",
      "referee_name": "",
      "weather": {},
      "home_ppg": 1.25,
      "away_ppg": 0.25,
      "team_a_xg_prematch": 1.16,
      "team_b_xg_prematch": 1.22,
      "btts_potential": 63.0,
      "o25_potential": 50.0,
      "o05HT_potential": 75.0,
      "odds_ft_1": 1.57,
      "odds_ft_x": 4.2,
      "odds_ft_2": 5.5,
      "homeGoalCount": 0,
      "awayGoalCount": 0,
      "status": "incomplete",
      "elapsed": 0,
      "boss_ai_decision": "STATUS: RISKY.\nREASON: Significant missing data (league context, standings, H2H, injuries, full odds). xG data (Remo 1.22) contradicts PPG (Remo 0.25) compared to Santos (xG 1.16, PPG 1.25).\nCONCLUSION: No Bet / Skip.",
      "prematch_comment": "STATUS: RISKY.\nREASON: Significant missing data (league context, standings, H2H, injuries, full odds). xG data (Remo 1.22) contradicts PPG (Remo 0.25) compared to Santos (xG 1.16, PPG 1.25).\nCONCLUSION: No Bet / Skip.",
      "ai_comment": "STATUS: RISKY.\nREASON: Significant missing data (league context, standings, H2H, injuries, full odds). xG data (Remo 1.22) contradicts PPG (Remo 0.25) compared to Santos (xG 1.16, PPG 1.25).\nCONCLUSION: No Bet / Skip."
    },
    {
      "id": "8432108",
      "source_ids": {
        "footystats": "8432108",
        "sportmonks": ""
      },
      "home_name": "Jaguares de Córdoba",
      "away_name": "Millonarios",
      "competition_name": "",
      "competition_id": 16614,
      "league_country": "",
      "league_country_image": "",
      "date_unix": 1775172000,
      "home_image": "teams/colombia-jaguares-de-cordoba-fc.png",
      "away_image": "teams/colombia-millonarios-fc-sa.png",
      "home_country": "Colombia",
      "away_country": "Colombia",
      "venue_name": "Estadio de Fútbol Jaraguay de Montería",
      "venue_city": ", Montería",
      "referee_name": "",
      "weather": {},
      "home_ppg": 0.79,
      "away_ppg": 1.5,
      "team_a_xg_prematch": 1.04,
      "team_b_xg_prematch": 1.56,
      "btts_potential": 57.0,
      "o25_potential": 61.0,
      "o05HT_potential": 72.0,
      "odds_ft_1": 3.5,
      "odds_ft_x": 3.3,
      "odds_ft_2": 1.84,
      "homeGoalCount": 0,
      "awayGoalCount": 0,
      "status": "incomplete",
      "elapsed": 0,
      "boss_ai_decision": "STATUS: All available data is consistent, strongly favoring Away. Missing odds for Over 2.5/BTTS, standings, H2H, and sidelined players prevent full cross-validation.\n\nREASON: Millonarios demonstrates clear superiority with significantly higher xG (1.56 vs 1.04) and PPG (1.5 vs 0.79). Bookmaker odds of 1.84 for Away Win confirm this strong favoritism.\n\nCONCLUSION: Away Win.",
      "prematch_comment": "STATUS: All available data is consistent, strongly favoring Away. Missing odds for Over 2.5/BTTS, standings, H2H, and sidelined players prevent full cross-validation.\n\nREASON: Millonarios demonstrates clear superiority with significantly higher xG (1.56 vs 1.04) and PPG (1.5 vs 0.79). Bookmaker odds of 1.84 for Away Win confirm this strong favoritism.\n\nCONCLUSION: Away Win.",
      "ai_comment": "STATUS: All available data is consistent, strongly favoring Away. Missing odds for Over 2.5/BTTS, standings, H2H, and sidelined players prevent full cross-validation.\n\nREASON: Millonarios demonstrates clear superiority with significantly higher xG (1.56 vs 1.04) and PPG (1.5 vs 0.79). Bookmaker odds of 1.84 for Away Win confirm this strong favoritism.\n\nCONCLUSION: Away Win."
    },
    {
      "id": "8419026",
      "source_ids": {
        "footystats": "8419026",
        "sportmonks": ""
      },
      "home_name": "Talleres Córdoba",
      "away_name": "Boca Juniors",
      "competition_name": "",
      "competition_id": 16571,
      "league_country": "",
      "league_country_image": "",
      "date_unix": 1775172600,
      "home_image": "teams/argentina-ca-talleres-de-cordoba.png",
      "away_image": "teams/argentina-ca-boca-juniors.png",
      "home_country": "Argentina",
      "away_country": "Argentina",
      "venue_name": "Estadio Juan Domingo Perón",
      "venue_city": "Calle Jujuy 2602 y Lope de Vega, Alta Córdoba, Ciudad de Córdoba, Provincia de Córdoba",
      "referee_name": "",
      "weather": {},
      "home_ppg": 1.64,
      "away_ppg": 1.55,
      "team_a_xg_prematch": 1.37,
      "team_b_xg_prematch": 1.4,
      "btts_potential": 50.0,
      "o25_potential": 36.0,
      "o05HT_potential": 45.0,
      "odds_ft_1": 2.9,
      "odds_ft_x": 2.78,
      "odds_ft_2": 2.89,
      "homeGoalCount": 0,
      "awayGoalCount": 0,
      "status": "incomplete",
      "elapsed": 0,
      "boss_ai_decision": "STATUS: RISKY\nREASON: Critical data points, including model predictions, league standings, H2H, key injuries, and specific odds for O/U and BTTS, are missing. Available data shows a very balanced match (xG 1.37/1.40, PPG 1.64/1.55, balanced 1X2 odds).\nCONCLUSION: No Bet / Skip",
      "prematch_comment": "STATUS: RISKY\nREASON: Critical data points, including model predictions, league standings, H2H, key injuries, and specific odds for O/U and BTTS, are missing. Available data shows a very balanced match (xG 1.37/1.40, PPG 1.64/1.55, balanced 1X2 odds).\nCONCLUSION: No Bet / Skip",
      "ai_comment": "STATUS: RISKY\nREASON: Critical data points, including model predictions, league standings, H2H, key injuries, and specific odds for O/U and BTTS, are missing. Available data shows a very balanced match (xG 1.37/1.40, PPG 1.64/1.55, balanced 1X2 odds).\nCONCLUSION: No Bet / Skip"
    },
    {
      "id": "8409520",
      "source_ids": {
        "footystats": "8409520",
        "sportmonks": ""
      },
      "home_name": "Bragantino",
      "away_name": "Flamengo",
      "competition_name": "",
      "competition_id": 16544,
      "league_country": "",
      "league_country_image": "",
      "date_unix": 1775176200,
      "home_image": "teams/brazil-clube-atletico-bragantino.png",
      "away_image": "teams/brazil-cr-flamengo.png",
      "home_country": "Brazil",
      "away_country": "Brazil",
      "venue_name": "Estádio Nabi Abi Chedid",
      "venue_city": "Rua Emílio Coleta, Bragança Paulista, São Paulo",
      "referee_name": "",
      "weather": {},
      "home_ppg": 1.0,
      "away_ppg": 1.75,
      "team_a_xg_prematch": 1.49,
      "team_b_xg_prematch": 1.29,
      "btts_potential": 75.0,
      "o25_potential": 63.0,
      "o05HT_potential": 88.0,
      "odds_ft_1": 3.9,
      "odds_ft_x": 3.4,
      "odds_ft_2": 1.95,
      "homeGoalCount": 0,
      "awayGoalCount": 0,
      "status": "incomplete",
      "elapsed": 0,
      "boss_ai_decision": "STATUS: RISKY.\nREASON: Extensive critical data missing, including model predictions, league standings, H2H, key sidelined players, and specific market odds (Over 2.5, BTTS, 1H O0.5, Team Total Goals). Available xG and PPG data present minor conflicts regarding team strength assessment.\nCONCLUSION: No Bet / Skip.",
      "prematch_comment": "STATUS: RISKY.\nREASON: Extensive critical data missing, including model predictions, league standings, H2H, key sidelined players, and specific market odds (Over 2.5, BTTS, 1H O0.5, Team Total Goals). Available xG and PPG data present minor conflicts regarding team strength assessment.\nCONCLUSION: No Bet / Skip.",
      "ai_comment": "STATUS: RISKY.\nREASON: Extensive critical data missing, including model predictions, league standings, H2H, key sidelined players, and specific market odds (Over 2.5, BTTS, 1H O0.5, Team Total Goals). Available xG and PPG data present minor conflicts regarding team strength assessment.\nCONCLUSION: No Bet / Skip."
    },
    {
      "id": "8409773",
      "source_ids": {
        "footystats": "8409773",
        "sportmonks": ""
      },
      "home_name": "Palmeiras",
      "away_name": "Grêmio",
      "competition_name": "",
      "competition_id": 16544,
      "league_country": "",
      "league_country_image": "",
      "date_unix": 1775176200,
      "home_image": "teams/brazil-se-palmeiras.png",
      "away_image": "teams/brazil-gremio-fb-porto-alegrense.png",
      "home_country": "Brazil",
      "away_country": "Brazil",
      "venue_name": "Allianz Parque",
      "venue_city": "Rua Turiaçu 1840, Perdizes, São Paulo, São Paulo",
      "referee_name": "",
      "weather": {},
      "home_ppg": 3.0,
      "away_ppg": 0.25,
      "team_a_xg_prematch": 1.66,
      "team_b_xg_prematch": 1.06,
      "btts_potential": 75.0,
      "o25_potential": 63.0,
      "o05HT_potential": 88.0,
      "odds_ft_1": 1.53,
      "odds_ft_x": 4.33,
      "odds_ft_2": 5.75,
      "homeGoalCount": 0,
      "awayGoalCount": 0,
      "status": "incomplete",
      "elapsed": 0,
      "boss_ai_decision": "STATUS: RISKY.\nREASON: Significant data missing (model predictions, standings, H2H, key injuries, specific odds for O2.5/BTTS). However, Palmeiras exhibits extreme dominance (PPG 3.0 vs 0.25, xG 1.66 vs 1.06). First Half Over 0.5 shows the highest potential (88%).\nCONCLUSION: First Half Over 0.5.",
      "prematch_comment": "STATUS: RISKY.\nREASON: Significant data missing (model predictions, standings, H2H, key injuries, specific odds for O2.5/BTTS). However, Palmeiras exhibits extreme dominance (PPG 3.0 vs 0.25, xG 1.66 vs 1.06). First Half Over 0.5 shows the highest potential (88%).\nCONCLUSION: First Half Over 0.5.",
      "ai_comment": "STATUS: RISKY.\nREASON: Significant data missing (model predictions, standings, H2H, key injuries, specific odds for O2.5/BTTS). However, Palmeiras exhibits extreme dominance (PPG 3.0 vs 0.25, xG 1.66 vs 1.06). First Half Over 0.5 shows the highest potential (88%).\nCONCLUSION: First Half Over 0.5."
    },
    {
      "id": "8432017",
      "source_ids": {
        "footystats": "8432017",
        "sportmonks": ""
      },
      "home_name": "Once Caldas",
      "away_name": "Independiente Medellín",
      "competition_name": "",
      "competition_id": 16614,
      "league_country": "",
      "league_country_image": "",
      "date_unix": 1775179800,
      "home_image": "teams/colombia-once-caldas-sa.png",
      "away_image": "teams/colombia-deportivo-independiente-medellin.png",
      "home_country": "Colombia",
      "away_country": "Colombia",
      "venue_name": "Estadio Palogrande",
      "venue_city": "Carrera 24 # 64 - 00, Manizales",
      "referee_name": "",
      "weather": {},
      "home_ppg": 1.71,
      "away_ppg": 1.23,
      "team_a_xg_prematch": 1.52,
      "team_b_xg_prematch": 1.54,
      "btts_potential": 82.0,
      "o25_potential": 60.0,
      "o05HT_potential": 78.0,
      "odds_ft_1": 2.12,
      "odds_ft_x": 3.2,
      "odds_ft_2": 2.96,
      "homeGoalCount": 0,
      "awayGoalCount": 0,
      "status": "incomplete",
      "elapsed": 0,
      "boss_ai_decision": "STATUS: RISKY.\nREASON: Significant data missing (model predictions, standings, H2H, specific O/U and BTTS odds). XG values (1.52 H, 1.54 A) suggest an extremely even contest, conflicting with home team favored odds and PPG.\nCONCLUSION: No Bet / Skip",
      "prematch_comment": "STATUS: RISKY.\nREASON: Significant data missing (model predictions, standings, H2H, specific O/U and BTTS odds). XG values (1.52 H, 1.54 A) suggest an extremely even contest, conflicting with home team favored odds and PPG.\nCONCLUSION: No Bet / Skip",
      "ai_comment": "STATUS: RISKY.\nREASON: Significant data missing (model predictions, standings, H2H, specific O/U and BTTS odds). XG values (1.52 H, 1.54 A) suggest an extremely even contest, conflicting with home team favored odds and PPG.\nCONCLUSION: No Bet / Skip"
    }
  ],
  "updated_at": "2026-04-02T06:44:13.097720Z"
}